yahpdf/__init__.py
yahpdf/pdf_tool.py
yahpdf-0.1.2.dist-info/LICENSE
yahpdf-0.1.2.dist-info/METADATA
yahpdf-0.1.2.dist-info/WHEEL
yahpdf-0.1.2.dist-info/entry_points.txt
yahpdf-0.1.2.dist-info/top_level.txt
yahpdf-0.1.2.dist-info/RECORD
