Metadata-Version: 2.1
Name: yahpdf
Version: 0.1.2
Summary: A CLI tool for analyzing PDF files
Home-page: https://github.com/yaya2devops/yahpdf
Author: Yahya Abulhaj
Author-email: dev@yahya-abulhaj.dev
Classifier: Programming Language :: Python :: 3
Classifier: License :: OSI Approved :: MIT License
Classifier: Operating System :: OS Independent
Requires-Python: >=3.6
License-File: LICENSE
Requires-Dist: PyPDF2
Requires-Dist: matplotlib
Requires-Dist: wordcloud
